[ {
  "id" : 1,
  "name" : "Casa Cristiano Ronaldo",
  "districtId" : 1,
  "rooms" : [ {
    "name" : "Quarto",
    "width" : 6.0,
    "length" : 3.0
  }, {
    "name" : "Cozinha",
    "width" : 3.0,
    "length" : 3.0
  } ]
}, {
  "id" : 2,
  "name" : "Lavoura do Mauri",
  "districtId" : 1,
  "rooms" : [ {
    "name" : "Quarto",
    "width" : 6.0,
    "length" : 3.0
  }, {
    "name" : "Cozinha",
    "width" : 3.0,
    "length" : 3.0
  } ]
}, {
  "id" : 3,
  "name" : "Casa Messi",
  "districtId" : 0,
  "rooms" : [ {
    "name" : "Quarto",
    "width" : 6.0,
    "length" : 3.0
  }, {
    "name" : "Cozinha",
    "width" : 3.0,
    "length" : 3.0
  } ]
} ]